readlike.py
readlike-0.1.3.dist-info/METADATA
readlike-0.1.3.dist-info/RECORD
readlike-0.1.3.dist-info/WHEEL
readlike-0.1.3.dist-info/top_level.txt
