Metadata-Version: 2.1
Name: readlike
Version: 0.1.3
Summary: GNU Readline-like line editing module
Home-page: https://github.com/jangler/readlike
Author: Brandon Mulcahy
Author-email: brandon@lightcones.net
License: MIT
Keywords: line editing,readlike,readline,urwid
Platform: UNKNOWN
Classifier: Development Status :: 5 - Production/Stable
Classifier: Intended Audience :: Developers
Classifier: License :: OSI Approved :: MIT License
Classifier: Operating System :: OS Independent
Classifier: Programming Language :: Python :: 2
Classifier: Programming Language :: Python :: 2.7
Classifier: Programming Language :: Python :: 3
Classifier: Programming Language :: Python :: 3.4
Classifier: Programming Language :: Python
Classifier: Topic :: Software Development :: Libraries :: Python Modules
Classifier: Topic :: Text Processing
